mutts/__init__.py
mutts/cli.py
mutts/retriever.py
mutts/spreadsheet.py
mutts/static-excel-tabs/JGI.Metagenome.NA.v15.xlsx
mutts-1.0.5.dist-info/METADATA
mutts-1.0.5.dist-info/WHEEL
mutts-1.0.5.dist-info/entry_points.txt
mutts-1.0.5.dist-info/RECORD
