Metadata-Version: 2.4
Name: mutts
Version: 1.0.5
Summary: Metadata for User facility Template Transformations
License: MIT
Keywords: NMDC,US DOE user facilities,metadata translation
Author: Sujay Patil
Author-email: spatil@lbl.gov
Requires-Python: >=3.12,<4.0
Classifier: Development Status :: 4 - Beta
Classifier: License :: OSI Approved :: MIT License
Classifier: Programming Language :: Python :: 3
Classifier: Programming Language :: Python :: 3.12
Classifier: Programming Language :: Python :: 3.13
Classifier: Programming Language :: Python :: 3.14
Requires-Dist: click (>=8.1.7,<9.0.0)
Requires-Dist: openpyxl (>=3.1.0,<4.0.0)
Requires-Dist: pandas (>=2.2.0,<3.0.0)
Requires-Dist: python-dotenv (>=1.0.0,<2.0.0)
Requires-Dist: requests (>=2.32.0,<3.0.0)
Project-URL: Homepage, https://github.com/microbiomedata/metadata-for-user-facility-template-transformations
Project-URL: Repository, https://github.com/microbiomedata/metadata-for-user-facility-template-transformations
